<?xml version="1.0" encoding="UTF-8"?>
<!DOCTYPE resources PUBLIC "-//GlassFish.org//DTD GlassFish Application Server 3.1 Resource Definitions//EN" "http://glassfish.org/dtds/glassfish-resources_1_5.dtd">
<resources>
    <jdbc-connection-pool
        datasource-classname="org.postgresql.ds.PGSimpleDataSource"
        res-type="javax.sql.DataSource" name="ZemiakMovies__pool">
      <property name="portNumber" value="5432"></property>
      <property name="databaseName" value="movies"></property>
      <property name="serverName" value="movies-db"></property>
      <property name="user" value="movies_user"></property>
      <property name="password" value="movies/0"></property>
    </jdbc-connection-pool>

    <jdbc-resource pool-name="ZemiakMovies__pool" jndi-name="jdbc/ZemiakMovies"></jdbc-resource>

    <mail-resource host="lenovo-server.local" jndi-name="java:/movies/mail/default"
                   from="anonymous@zemiak.com" user="anonymous">
    </mail-resource>
</resources>
